setup.py
django_mangopay.egg-info/PKG-INFO
django_mangopay.egg-info/SOURCES.txt
django_mangopay.egg-info/dependency_links.txt
django_mangopay.egg-info/requires.txt
django_mangopay.egg-info/top_level.txt
mangopay/__init__.py
mangopay/client.py
mangopay/constants.py
mangopay/models.py
mangopay/tasks.py
mangopay/tests/__init__.py
mangopay/tests/bank_account.py
mangopay/tests/card.py
mangopay/tests/card_registration.py
mangopay/tests/client.py
mangopay/tests/document.py
mangopay/tests/factories.py
mangopay/tests/page.py
mangopay/tests/payin.py
mangopay/tests/payout.py
mangopay/tests/refund.py
mangopay/tests/users.py
mangopay/tests/wallet.py