Metadata-Version: 1.1
Name: django-mangopay
Version: 1.0.0
Summary: Django package that helps in your Mangopay integration
Home-page: http://github.com/FundedByMe/django-mangopay
Author: Rebecca Meritz
Author-email: rebecca@fundedbyme.com
License: UNKNOWN
Platform: UNKNOWN
Classifier: Framework :: Django
Classifier: Intended Audience :: Developers
Classifier: Intended Audience :: System Administrators
Classifier: Operating System :: OS Independent
Classifier: Topic :: Software Development
